LICENSE
README.md
setup.py
django_mdmail/__init__.py
django_mdmail.egg-info/PKG-INFO
django_mdmail.egg-info/SOURCES.txt
django_mdmail.egg-info/dependency_links.txt
django_mdmail.egg-info/requires.txt
django_mdmail.egg-info/top_level.txt