Metadata-Version: 2.1
Name: django-mdmail
Version: 0.5.0
Summary: Markdown-mail support for Django via `mdmail`.
Home-page: https://github.com/binary-is/django_mdmail
Author: Helgi Hrafn Gunnarsson
Author-email: helgi@binary.is
License: MIT
Platform: UNKNOWN
Classifier: Development Status :: 4 - Beta
Classifier: Framework :: Django
Classifier: Intended Audience :: Developers
Classifier: License :: OSI Approved :: MIT License
Classifier: Operating System :: OS Independent
Classifier: Programming Language :: Python :: 3
Classifier: Topic :: Internet :: WWW/HTTP
Classifier: Topic :: Software Development :: Libraries :: Python Modules
Classifier: Topic :: Text Processing :: Filters
Classifier: Topic :: Text Processing :: Markup :: HTML
